godaddypy/__init__.py
godaddypy/__main__.py
godaddypy/account.py
godaddypy/client.py
GoDaddyPy-2.5.1.dist-info/LICENSE
GoDaddyPy-2.5.1.dist-info/METADATA
GoDaddyPy-2.5.1.dist-info/WHEEL
GoDaddyPy-2.5.1.dist-info/top_level.txt
GoDaddyPy-2.5.1.dist-info/RECORD
