Metadata-Version: 2.1
Name: GoDaddyPy
Version: 2.5.1
Summary: A very simple python client used to update the IP address in A records for GoDaddy managed domains.
Home-page: https://github.com/eXamadeus/godaddypy
Author: Julian Coy
Author-email: julian.calvin.coy@gmail.com
Project-URL: Source, https://github.com/eXamadeus/godaddypy
Classifier: Development Status :: 5 - Production/Stable
Classifier: Intended Audience :: Developers
Classifier: Intended Audience :: System Administrators
Classifier: Topic :: Internet :: Name Service (DNS)
Classifier: License :: OSI Approved :: BSD License
Classifier: Natural Language :: English
Classifier: Programming Language :: Python :: 2
Classifier: Programming Language :: Python :: 2.7
Classifier: Programming Language :: Python :: 3
Classifier: Programming Language :: Python :: 3.2
Classifier: Programming Language :: Python :: 3.3
Classifier: Programming Language :: Python :: 3.4
Classifier: Programming Language :: Python :: 3.5
Classifier: Programming Language :: Python :: 3.6
Classifier: Programming Language :: Python :: 3.7
License-File: LICENSE
Requires-Dist: requests >=2.4
